[
    {
        "nom": "Hp PC PORTABLE HP ELITEBOOK 840 G5 8ÉME GÉN-CORE I5-8Go-256 Go SSD-Remise à neuf",
        "prix": "2,990.00 Dhs"
    },
    {
        "nom": "Hp Laptop EliteBook CORE i5-6eme RAM 8Go/SSD 256Go Pack Gratuit  -Remis à neuf",
        "prix": "2,599.00 Dhs"
    },
    {
        "nom": "Hp EliteBook 840 14Pouce G3 Core i5 6eme Grd 8Go DDR4-256 M.2 SSD Remis a Neuf",
        "prix": "2,550.00 Dhs"
    },
    {
        "nom": "Lenovo PC PORTABLE  Thinkpad-T460 Core i5 RAM 8GB 500 HDD-6ème Génération-Remis a Neuf",
        "prix": "1,999.00 Dhs"
    },
    {
        "nom": "Lenovo PC PORTABLE  Thinkpad-L430 Core i5-5éme Génération-RAM-8GB-500 HDD-AZERTY-Remis a Neuf",
        "prix": "1,979.00 Dhs"
    },
    {
        "nom": "Apple Macbook Pro Retina 13,3\" -2015 -INTEL CORE i5-RAM 8Go-SSD 128Go - Remis a neuf",
        "prix": "3,399.00 Dhs"
    },
    {
        "nom": "Hp PC PORTABLE ELITEBOOK 840 G5 8ÉME GÉN-CORE I5-8Go-256 Go SSD-Remis à neuf",
        "prix": "3,150.00 Dhs"
    },
    {
        "nom": "Lenovo PC PORTABLE LENOVO THINKPAD T540P-I5-8G-500Go-FULL HD-REMISE A NEUF",
        "prix": "1,999.00 Dhs"
    },
    {
        "nom": "Hp PC Portable Probook 640 Core intel i3-500Go-RAM 8GB 14\"- remis a neuf",
        "prix": "3,699.00 Dhs"
    },
    {
        "nom": "Hp PC Portable ELITEBOOK X360 G2 I5-7éme -8GB- 256GB SSD - TACTILE -REMIS À NEUF",
        "prix": "4,549.00 Dhs"
    },
    {
        "nom": "Apple Macbook air 2020-Retina 13,3\" -INTEL i3 -RAM 8Go-SSD 256Go-Batterie10h -remis a neuf/",
        "prix": "5,999.00 Dhs"
    },
    {
        "nom": "Hp PC PORTABLE Slim  CORE i5 6eme RAM 8Go DDR4 - HDD 500Go -Remis a Neuf",
        "prix": "2,290.00 Dhs"
    },
    {
        "nom": "DELL LATITUDE E5540 CORE I3-4030U (1,90Ghz)- RAM 4Go - 128Go SSD - Remis à Neuf",
        "prix": "1,349.00 Dhs"
    },
    {
        "nom": "DELL LATITUDE E5540 CORE I3-4030U (1,90Ghz)- RAM 4Go - HDD 500Go ( Remis à Neuf )",
        "prix": "1,399.00 Dhs"
    },
    {
        "nom": "Lenovo PC PORTABLE THINKPAD T540P-I5-8G-256Go SSD-FULL HD-REMIS A NEUF",
        "prix": "2,299.00 Dhs"
    },
    {
        "nom": "DELL LATITUDE E5530 - CORE I5-3210M (2.5GHz) 15.6\" HD - 8Go , 256Go SSD Go ( Remis à Neuf ) - AZERTY",
        "prix": "1,799.00 Dhs"
    },
    {
        "nom": "Hp PC Portable Probook 640 Core intel i3-1000Go-RAM 16GB 14\"- remis a neuf",
        "prix": "2,999.00 Dhs"
    },
    {
        "nom": "Lenovo PC PORTABLE LENOVO Thinkpad-T440 Core i5 RAM 8GB 500 HDD -Remis a Neuf",
        "prix": "1,799.00 Dhs"
    },
    {
        "nom": "Hp NoteBook Elite x2 PRO G3-Intel® i5-8e Génération- RAM 16Go-SSD 512Go-TACTILE-AZERTY -REMIS À NEUF",
        "prix": "4,949.00 Dhs"
    },
    {
        "nom": "Hp Pc portable Probook 640 G5 ntel® Core I5-8365U - 8go- SSD 256Go- Remis a neuf",
        "prix": "3,000.00 Dhs"
    },
    {
        "nom": "Lenovo ThinkPad X220, Intel Core i5 - RAM 8Go-HDD 320Go + CARTABLE - REMIS A NEUF/",
        "prix": "1,599.00 Dhs"
    },
    {
        "nom": "Lenovo ThinkPad X220, Intel Core i5 -intel génération RAM 8Go, HDD 320Go - REMIS A NEUF/",
        "prix": "1,599.00 Dhs"
    },
    {
        "nom": "Apple MacBook Pro RETINA 13.3 -2015-Core I5- RAM 8Go-DISK DUR 256GO SSD–QUERTY- REMIS A NEUF/",
        "prix": "3,499.00 Dhs"
    },
    {
        "nom": "Hp EliteBook 840 G3 i5-6200U 2.30 GHz 8 Go 240 Go SSD  Remis a Neuf",
        "prix": "2,300.00 Dhs"
    },
    {
        "nom": "Asus Pc portable X515EA i7-1165G7 - 8Go/512Go SSD - 15.6\" Windows 11 AZERTY",
        "prix": "6,926.00 Dhs"
    },
    {
        "nom": "Hp Ordinateur EliteBook CORE i5-6eme RAM 32Go DDR4 - SSD 256Go -Remis a Neuf",
        "prix": "3,799.00 Dhs"
    },
    {
        "nom": "Hp Elitebook 820 G3 i7 6éme RAM 8GB DISK 256GB SSD ( Remis à Neuf ) - QWERTY",
        "prix": "2,892.00 Dhs"
    },
    {
        "nom": "Lenovo ThinkPad X240 Intel Core i3-4030U 1.9Ghz - RAM 8Go - SSD 256Go - 12.5\" (Remis à Neuf) - AZERTY",
        "prix": "1,599.00 Dhs"
    },
    {
        "nom": "Asus Pc portable G713 Ryzen 7-4800H 17,3 32Go 512Go SSD Win 10 GRAY RTX 3050 4G 12M",
        "prix": "14,499.00 Dhs"
    },
    {
        "nom": "Lenovo Notebook ThinkPad L390 YOGA  i5–8250U-8Go-256Go SSD-AVEC STYLET-TACTILE-AZERTY-REMIS A NEUF",
        "prix": "2,899.00 Dhs"
    },
    {
        "nom": "Hp PC Portable HP Probook 640 Core i3 4eme 320Gb 4GB RAM 14\"- remis a neuf - AZERTY",
        "prix": "1,599.00 Dhs"
    },
    {
        "nom": "Lenovo PC PORTABLE THINKPAD L530-I5-8G-250Go-FULL HD-AZERTY-REMIS A NEUF",
        "prix": "1,789.00 Dhs"
    },
    {
        "nom": "Hp EliteBook 840 G3 Core i5-16Go DDR4 -512Go SSD-15.6″ Full HD+Sacoch -Remis à Neuf - QWERTY",
        "prix": "3,199.00 Dhs"
    },
    {
        "nom": "Hp Probook 640 G5 ntel® Core i5-8365U - 16go- SSD 256Go+500Go HDD- Remis a neuf",
        "prix": "3,500.00 Dhs"
    },
    {
        "nom": "Hp PC Portable HP Probook 640 Core i3- 256Gb SSD- 8GB RAM -14\"- remis a neuf - AZERTY",
        "prix": "1,699.00 Dhs"
    },
    {
        "nom": "Apple Macbook air M1 2020-Retina 13,3\" -Apple M1 Chip-RAM 8Go-SSD 256Go-Batterie10h -remis a neuf/",
        "prix": "6,999.00 Dhs"
    },
    {
        "nom": "Hp PC Portable Probook 640 Core intel i3-500Go-RAM 8GB 14\"- remis a neuf",
        "prix": "2,599.00 Dhs"
    },
    {
        "nom": "Hp PC PORTABLE  ELITEBOOK 840 G5 8ÉME GÉN-CORE I5-8Go-256 Go SSD-Remis à neuf",
        "prix": "2,999.00 Dhs"
    },
    {
        "nom": "Lenovo PC PORTABLE  Thinkpad-L430-Core i5-RAM 8GB-500 HDD-AZERTY-Remis a Neuf",
        "prix": "1,999.00 Dhs"
    },
    {
        "nom": "Apple MacBook AIR 13 2015- Core I5- RAM 4Go- DISK DUR 128GO SSD – REMIS A NEUF/",
        "prix": "2,999.00 Dhs"
    }
]